CHANGELOG.rst
django_swagger_tester/__init__.py
django_swagger_tester/apps.py
django_swagger_tester/case_testers.py
django_swagger_tester/configuration.py
django_swagger_tester/drf_yasg.py
django_swagger_tester/exceptions.py
django_swagger_tester/loaders.py
django_swagger_tester/middleware.py
django_swagger_tester/migrations/0001_initial.py
django_swagger_tester/migrations/0002_auto_20200925_1145.py
django_swagger_tester/migrations/__init__.py
django_swagger_tester/models.py
django_swagger_tester/openapi.py
django_swagger_tester/schema_tester.py
django_swagger_tester/selectors.py
django_swagger_tester/static.py
django_swagger_tester/testing.py
django_swagger_tester/types.py
django_swagger_tester/utils.py
django_swagger_tester/validation.py
django_swagger_tester/views.py
django_swagger_tester-2.2.1.dist-info/LICENSE.txt
django_swagger_tester-2.2.1.dist-info/WHEEL
django_swagger_tester-2.2.1.dist-info/METADATA
django_swagger_tester-2.2.1.dist-info/RECORD
